adminutils/__init__.py
adminutils/actions.py
adminutils/decorators.py
adminutils/images.py
adminutils/logging.py
adminutils/widgets.py
adminutils/static/admin/css/object-actions.css
adminutils/static/admin/css/overrides.css
adminutils/static/admin/css/print.css
adminutils/templates/admin/generic_form.html
adminutils/templates/admin/rangefield.html
adminutils/templates/django_object_actions/change_form.html
adminutils/templates/django_object_actions/change_list.html
django_adminutils-0.0.28.dist-info/LICENSE
django_adminutils-0.0.28.dist-info/METADATA
django_adminutils-0.0.28.dist-info/WHEEL
django_adminutils-0.0.28.dist-info/top_level.txt
django_adminutils-0.0.28.dist-info/RECORD
