Metadata-Version: 2.2
Name: django-adminutils
Version: 0.0.28
Summary: Utilities to make working with the Django admin nicer.
Home-page: https://github.com/GaretJax/django-adminutils
Author: Jonathan Stoppani
Author-email: jonathan@stoppani.name
License: MIT
Classifier: Development Status :: 4 - Beta
Classifier: Intended Audience :: Developers
Classifier: License :: OSI Approved :: MIT License
Classifier: Operating System :: OS Independent
Classifier: Programming Language :: Python
Classifier: Programming Language :: Python :: 3
License-File: LICENSE
Requires-Dist: django-object-actions
Requires-Dist: django
Dynamic: author
Dynamic: author-email
Dynamic: classifier
Dynamic: description
Dynamic: home-page
Dynamic: license
Dynamic: requires-dist
Dynamic: summary
